G:\mnt\bc\mydev\GDGamesP\game.xml
                        <value>GetArgumentAsBoolean</value>
                        <value>SetCameraX</value>
                        <value>GetArgumentAsBoolean</value>
                        <value>SetCameraY</value>
                        <value>GetArgumentAsBoolean</value>
                                                <value>GetArgumentAsBoolean</value>
                        <value>SetCameraAngle</value>
                            <value>SmoothCamera::SmoothCamera::SetLeftwardSpeed</value>
                            <value>SmoothCamera::SmoothCamera::SetRightwardSpeed</value>
                            <value>SmoothCamera::SmoothCamera::SetUpwardSpeed</value>
                            <value>SmoothCamera::SmoothCamera::SetDownwardSpeed</value>
                            <value>SmoothCamera::SmoothCamera::SetLeftwardSpeedMax</value>
                            <value>SmoothCamera::SmoothCamera::SetRightwardSpeedMax</value>
                            <value>SmoothCamera::SmoothCamera::SetUpwardSpeedMax</value>
                            <value>SmoothCamera::SmoothCamera::SetDownwardSpeedMax</value>
                            <value>SmoothCamera::SmoothCamera::SetFollowFreeAreaLeft</value>
                            <value>SmoothCamera::SmoothCamera::SetFollowFreeAreaRight</value>
                            <value>SmoothCamera::SmoothCamera::SetFollowFreeAreaTop</value>
                            <value>SmoothCamera::SmoothCamera::SetFollowFreeAreaBottom</value>
                            <value>SmoothCamera::SmoothCamera::SetPropertyCameraDelay</value>
                            <value>SmoothCamera::SmoothCamera::PropertyIsCalledManually</value>
                            <value>SmoothCamera::SmoothCamera::DoMoveCameraCloser</value>
                            <value>SmoothCamera::SmoothCamera::SetPropertyIsCalledManually</value>
                            <value>SmoothCamera::SmoothCamera::DoMoveCameraCloser</value>
                            <value>SmoothCamera::SmoothCamera::UpdateDelayedPosition</value>
                            <value>SmoothCamera::SmoothCamera::UpdateForecastedPosition</value>
                            <value>SmoothCamera::SmoothCamera::PropertyFollowOnX</value>
                            <value>SmoothCamera::SmoothCamera::SetPropertyOldX</value>
                                <value>CameraX</value>
                                <value>SetCameraX</value>
                                    <value>CameraX</value>
                                    <value>SetCameraX</value>
                                <value>CameraX</value>
                                <value>SetCameraX</value>
                                    <value>CameraX</value>
                                    <value>SetCameraX</value>
                            <value>SmoothCamera::SmoothCamera::PropertyFollowOnY</value>
                            <value>SmoothCamera::SmoothCamera::SetPropertyOldY</value>
                                <value>CameraY</value>
                                <value>SetCameraY</value>
                                    <value>CameraY</value>
                                    <value>SetCameraY</value>
                                <value>CameraY</value>
                                <value>SetCameraY</value>
                                    <value>CameraY</value>
                                    <value>SetCameraY</value>
                            <value>SmoothCamera::SmoothCamera::SetPropertyWaitingEnd</value>
                            <value>SmoothCamera::SmoothCamera::SetPropertyWaitingSpeedXMax</value>
                            <value>SmoothCamera::SmoothCamera::SetPropertyWaitingSpeedYMax</value>
                            <value>SmoothCamera::SmoothCamera::SetPropertyCameraDelayCatchUpDuration</value>
                            <value>DebuggerTools::ConsoleLog</value>
                            <value>PrimitiveDrawing::FillOpacity</value>
                                <value>Egal</value>
                                <value>SmoothCamera::SmoothCamera::SetPropertyIndex</value>
                                <value>PrimitiveDrawing::OutlineColor</value>
                                <value>PrimitiveDrawing::BeginFillPath</value>
                                    <value>PrimitiveDrawing::PathLineTo</value>
                                    <value>SmoothCamera::SmoothCamera::SetPropertyIndex</value>
                                    <value>PrimitiveDrawing::EndFillPath</value>
                                    <value>SmoothCamera::SmoothCamera::PropertyFollowFreeAreaLeft</value>
                                    <value>SmoothCamera::SmoothCamera::PropertyFollowFreeAreaRight</value>
                                    <value>SmoothCamera::SmoothCamera::PropertyFollowFreeAreaTop</value>
                                    <value>SmoothCamera::SmoothCamera::PropertyFollowFreeAreaBottom</value>
                                <value>BuiltinCommonInstructions::Or</value>
                                <value>PrimitiveDrawing::OutlineColor</value>
                                <value>PrimitiveDrawing::Rectangle</value>
                                <value>PrimitiveDrawing::OutlineColor</value>
                                <value>PrimitiveDrawing::LineV2</value>
                                <value>PrimitiveDrawing::Circle</value>
                                <value>PrimitiveDrawing::LineV2</value>
                                <value>PrimitiveDrawing::LineV2</value>
                            <value>SmoothCamera::SmoothCamera::SetPropertyFollowOnX</value>
                            <value>GetArgumentAsBoolean</value>
                            <value>SmoothCamera::SmoothCamera::SetPropertyFollowOnX</value>
                            <value>SmoothCamera::SmoothCamera::SetPropertyFollowOnY</value>
                            <value>GetArgumentAsBoolean</value>
                            <value>SmoothCamera::SmoothCamera::SetPropertyFollowOnY</value>
                            <value>SmoothCamera::SmoothCamera::SetPropertyFollowFreeAreaTop</value>
                            <value>SmoothCamera::SmoothCamera::SetPropertyFollowFreeAreaTop</value>
                            <value>SmoothCamera::SmoothCamera::SetPropertyFollowFreeAreaTop</value>
                            <value>SmoothCamera::SmoothCamera::SetPropertyFollowFreeAreaBottom</value>
                            <value>SmoothCamera::SmoothCamera::SetPropertyLeftwardSpeedMax</value>
                            <value>SmoothCamera::SmoothCamera::SetPropertyLeftwardSpeedMax</value>
                            <value>SmoothCamera::SmoothCamera::SetPropertyUpwardSpeedMax</value>
                            <value>SmoothCamera::SmoothCamera::SetPropertyDownwardSpeedMax</value>
                            <value>SmoothCamera::SmoothCamera::SetPropertyLeftwardSpeed</value>
                            <value>SmoothCamera::SmoothCamera::SetPropertyLogLeftwardSpeed</value>
                            <value>SmoothCamera::SmoothCamera::SetPropertyRightwardSpeed</value>
                            <value>SmoothCamera::SmoothCamera::SetPropertyLogRightwardSpeed</value>
                            <value>SmoothCamera::SmoothCamera::SetPropertyDownwardSpeed</value>
                            <value>SmoothCamera::SmoothCamera::SetPropertyLogDownwardSpeed</value>
                            <value>SmoothCamera::SmoothCamera::SetPropertyUpwardSpeed</value>
                            <value>SmoothCamera::SmoothCamera::SetPropertyLogUpwardSpeed</value>
                            <value>SmoothCamera::SmoothCamera::SetPropertyCameraOffsetX</value>
                            <value>SmoothCamera::SmoothCamera::SetPropertyCameraOffsetY</value>
                            <value>SmoothCamera::SmoothCamera::SetPropertyForecastTime</value>
                            <value>SmoothCamera::SmoothCamera::SetPropertyCameraDelay</value>
                            <value>SetReturnNumber</value>
                            <value>SetReturnNumber</value>
                            <value>SetReturnNumber</value>
                            <value>SetReturnNumber</value>
                            <value>SmoothCamera::SmoothCamera::IsWaiting</value>
                            <value>Egal</value>
                            <value>ObjectVariablePushNumber</value>
                            <value>ObjectVariablePushNumber</value>
                            <value>ObjectVariablePushNumber</value>
                            <value>SmoothCamera::SmoothCamera::SetPropertyDelayedCenterX</value>
                            <value>SmoothCamera::SmoothCamera::SetPropertyDelayedCenterY</value>
                            <value>SmoothCamera::SmoothCamera::IsDelayed</value>
                            <value>SmoothCamera::SmoothCamera::AddForecastHistoryPosition</value>
                                <value>SmoothCamera::SmoothCamera::IsDelayed</value>
                                <value>SmoothCamera::SmoothCamera::IsWaiting</value>
                            <value>BuiltinCommonInstructions::Or</value>
                            <value>ObjectVariablePushNumber</value>
                            <value>ObjectVariablePushNumber</value>
                            <value>ObjectVariablePushNumber</value>
                                <value>Egal</value>
                                                                <value>SmoothCamera::SmoothCamera::AddForecastHistoryPosition</value>
                                <value>ObjectVariableRemoveAt</value>
                                <value>ObjectVariableRemoveAt</value>
                                <value>ObjectVariableRemoveAt</value>
                                <value>SmoothCamera::SmoothCamera::SetPropertyDelayedCenterX</value>
                                <value>SmoothCamera::SmoothCamera::SetPropertyDelayedCenterY</value>
                                <value>Egal</value>
                                                                    <value>SmoothCamera::SmoothCamera::IsWaiting</value>
                                    <value>SmoothCamera::SmoothCamera::SetPropertyCameraExtraDelay</value>
                                        <value>DebuggerTools::ConsoleLog</value>
                                    <value>SmoothCamera::SmoothCamera::SetPropertyDelayedCenterX</value>
                                    <value>SmoothCamera::SmoothCamera::SetPropertyDelayedCenterY</value>
                            <value>SmoothCamera::SmoothCamera::IsDelayed</value>
                            <value>SmoothCamera::SmoothCamera::IsWaiting</value>
                            <value>ObjectVariableClearChildren</value>
                            <value>ObjectVariableClearChildren</value>
                            <value>ObjectVariableClearChildren</value>
                            <value>SmoothCamera::SmoothCamera::IsWaiting</value>
                                                        <value>SmoothCamera::SmoothCamera::SetPropertyCameraDelayCatchUpSpeed</value>
                                <value>DebuggerTools::ConsoleLog</value>
                            <value>SmoothCamera::SmoothCamera::IsWaiting</value>
                            <value>SmoothCamera::SmoothCamera::PropertyCameraExtraDelay</value>
                            <value>SmoothCamera::SmoothCamera::SetPropertyCameraExtraDelay</value>
                                <value>DebuggerTools::ConsoleLog</value>
                            <value>Egal</value>
                            <value>SetReturnBoolean</value>
                            <value>SetReturnNumber</value>
                            <value>SmoothCamera::SmoothCamera::PropertyWaitingEnd</value>
                            <value>SetReturnBoolean</value>
                                <value>SmoothCamera::SmoothCamera::PropertyForecastHistoryDuration</value>
                                <value>SmoothCamera::SmoothCamera::PropertyForecastTime</value>
                            <value>BuiltinCommonInstructions::Or</value>
                            <value>ObjectVariablePushNumber</value>
                            <value>ObjectVariablePushNumber</value>
                            <value>ObjectVariablePushNumber</value>
                                <value>Egal</value>
                                                                <value>ObjectVariableRemoveAt</value>
                                <value>ObjectVariableRemoveAt</value>
                                <value>ObjectVariableRemoveAt</value>
                            <value>SmoothCamera::SmoothCamera::SetPropertyForecastedX</value>
                            <value>SmoothCamera::SmoothCamera::SetPropertyForecastedY</value>
                            <value>Egal</value>
                                <value>SmoothCamera::SmoothCamera::PropertyForecastHistoryDuration</value>
                                <value>SmoothCamera::SmoothCamera::PropertyForecastTime</value>
                            <value>BuiltinCommonInstructions::Or</value>
                                    <value>SmoothCamera::SmoothCamera::SetPropertyForecastHistoryMeanX</value>
                                    <value>SmoothCamera::SmoothCamera::SetPropertyIndex</value>
                                    <value>SmoothCamera::SmoothCamera::SetPropertyForecastHistoryMeanX</value>
                                    <value>SmoothCamera::SmoothCamera::SetPropertyIndex</value>
                                    <value>SmoothCamera::SmoothCamera::SetPropertyForecastHistoryMeanX</value>
                                    <value>SmoothCamera::SmoothCamera::SetPropertyForecastHistoryMeanY</value>
                                    <value>SmoothCamera::SmoothCamera::SetPropertyIndex</value>
                                    <value>SmoothCamera::SmoothCamera::SetPropertyForecastHistoryMeanY</value>
                                    <value>SmoothCamera::SmoothCamera::SetPropertyIndex</value>
                                    <value>SmoothCamera::SmoothCamera::SetPropertyForecastHistoryMeanY</value>
                                    <value>DebuggerTools::ConsoleLog</value>
                                    <value>SmoothCamera::SmoothCamera::SetPropertyForecastHistoryVarianceX</value>
                                    <value>SmoothCamera::SmoothCamera::SetPropertyForecastHistoryVarianceY</value>
                                    <value>SmoothCamera::SmoothCamera::SetPropertyForecastHistoryCovariance</value>
                                    <value>SmoothCamera::SmoothCamera::SetPropertyIndex</value>
                                    <value>SmoothCamera::SmoothCamera::SetPropertyForecastHistoryVarianceX</value>
                                    <value>SmoothCamera::SmoothCamera::SetPropertyForecastHistoryVarianceY</value>
                                    <value>SmoothCamera::SmoothCamera::SetPropertyForecastHistoryCovariance</value>
                                    <value>SmoothCamera::SmoothCamera::SetPropertyIndex</value>
                                    <value>DebuggerTools::ConsoleLog</value>
                                    <value>Egal</value>
                                    <value>Egal</value>
                                    <value>SmoothCamera::SmoothCamera::SetPropertyForecastedX</value>
                                    <value>SmoothCamera::SmoothCamera::SetPropertyForecastedY</value>
                                        <value>Egal</value>
                                        <value>Egal</value>
                                    <value>BuiltinCommonInstructions::Or</value>
                                            <value>Egal</value>
                                            <value>SmoothCamera::SmoothCamera::SetPropertyForecastHistoryLinearA</value>
                                            <value>SmoothCamera::SmoothCamera::SetPropertyForecastHistoryLinearB</value>
                                                <value>DebuggerTools::ConsoleLog</value>
                                                    <value>SmoothCamera::SmoothCamera::ProjectHistoryEnds</value>
                                            <value>Egal</value>
                                            <value>SmoothCamera::SmoothCamera::SetPropertyForecastHistoryLinearA</value>
                                            <value>SmoothCamera::SmoothCamera::SetPropertyForecastHistoryLinearB</value>
                                                <value>DebuggerTools::ConsoleLog</value>
                                                    <value>SmoothCamera::SmoothCamera::ProjectHistoryEnds</value>
                                                    <value>SmoothCamera::SmoothCamera::SetPropertyIndex</value>
                                                    <value>SmoothCamera::SmoothCamera::SetPropertyProjectedOldestX</value>
                                                    <value>SmoothCamera::SmoothCamera::SetPropertyProjectedOldestY</value>
                                                    <value>SmoothCamera::SmoothCamera::SetPropertyIndex</value>
                                                    <value>SmoothCamera::SmoothCamera::SetPropertyProjectedNewestX</value>
                                                    <value>SmoothCamera::SmoothCamera::SetPropertyProjectedNewestY</value>
                                                <value>DebuggerTools::ConsoleLog</value>
                                                <value>DebuggerTools::ConsoleLog</value>
                                                <value>SmoothCamera::SmoothCamera::SetPropertyForecastedX</value>
                                                <value>SmoothCamera::SmoothCamera::SetPropertyForecastedY</value>
                                                <value>DebuggerTools::ConsoleLog</value>
                            <value>SmoothCamera::SmoothCamera::SetPropertyProjectedNewestX</value>
                            <value>SmoothCamera::SmoothCamera::SetPropertyProjectedNewestY</value>
                            <value>SmoothCamera::SmoothCamera::SetPropertyProjectedOldestX</value>
                            <value>SmoothCamera::SmoothCamera::SetPropertyProjectedOldestY</value>
                            <value>SetReturnNumber</value>
                                                                                                                                                                                                                                                                                                                                                            <value>PlatformBehavior::IsJumping</value>
                            <value>PlatformBehavior::IsFalling</value>
                            <value>SmoothCamera::SmoothCamera::SetFollowFreeAreaBottom</value>
                            <value>SmoothCamera::SmoothCamera::SetFollowFreeAreaTop</value>
                            <value>SmoothCamera::SmoothCamera::SetUpwardSpeed</value>
                            <value>SmoothCamera::SmoothCamera::SetDownwardSpeed</value>
                            <value>SmoothCamera::SmoothCamera::SetUpwardSpeedMax</value>
                            <value>SmoothCamera::SmoothCamera::SetDownwardSpeedMax</value>
                                <value>PlatformBehavior::IsJumping</value>
                                <value>PlatformBehavior::IsFalling</value>
                            <value>BuiltinCommonInstructions::Or</value>
                            <value>SmoothCamera::SmoothCamera::SetFollowFreeAreaBottom</value>
                            <value>SmoothCamera::SmoothCamera::SetFollowFreeAreaTop</value>
                            <value>SmoothCamera::SmoothCamera::SetUpwardSpeed</value>
                            <value>SmoothCamera::SmoothCamera::SetDownwardSpeed</value>
                            <value>SmoothCamera::SmoothCamera::SetUpwardSpeedMax</value>
                            <value>SmoothCamera::SmoothCamera::SetDownwardSpeedMax</value>
                                                                                <value>0.95</value>
                <value>0.95</value>
                                                                                                                        <value>BuiltinCommonInstructions::CompareNumbers</value>
                        <value>SetReturnNumber</value>
                        <value>BuiltinCommonInstructions::CompareNumbers</value>
                        <value>SetReturnNumber</value>
                        <value>SetReturnNumber</value>
                                <value>TopDownMovementBehavior::TopDownMovementBehavior::IsUsingControl</value>
                                                                    <value>TopDownMovementBehavior::TopDownMovementBehavior::IsUsingControl</value>
                                    <value>PixelPerfectMovement::PixelPerfectTopDownMovement::SetPropertyTargetX</value>
                                    <value>PixelPerfectMovement::PixelPerfectTopDownMovement::SetPropertyTargetDirectionX</value>
                                        <value>DebuggerTools::ConsoleLog</value>
                                <value>TopDownMovementBehavior::TopDownMovementBehavior::IsUsingControl</value>
                                                                    <value>TopDownMovementBehavior::TopDownMovementBehavior::IsUsingControl</value>
                                    <value>PixelPerfectMovement::PixelPerfectTopDownMovement::SetPropertyTargetX</value>
                                    <value>PixelPerfectMovement::PixelPerfectTopDownMovement::SetPropertyTargetDirectionX</value>
                                        <value>DebuggerTools::ConsoleLog</value>
                                <value>TopDownMovementBehavior::TopDownMovementBehavior::IsUsingControl</value>
                                <value>TopDownMovementBehavior::TopDownMovementBehavior::IsUsingControl</value>
                                                                        <value>PixelPerfectMovement::PixelPerfectTopDownMovement::PropertyTargetDirectionX</value>
                                    <value>TopDownMovementBehavior::TopDownMovementBehavior::SetVelocityX</value>
                                                                        <value>PixelPerfectMovement::PixelPerfectTopDownMovement::PropertyTargetDirectionX</value>
                                    <value>TopDownMovementBehavior::TopDownMovementBehavior::SetVelocityX</value>
                                                                                        <value>PixelPerfectMovement::PixelPerfectTopDownMovement::PropertyTargetDirectionX</value>
                                        <value>BuiltinCommonInstructions::And</value>
                                                                                        <value>PixelPerfectMovement::PixelPerfectTopDownMovement::PropertyTargetDirectionX</value>
                                        <value>BuiltinCommonInstructions::And</value>
                                    <value>BuiltinCommonInstructions::Or</value>
                                                                        <value>PixelPerfectMovement::PixelPerfectTopDownMovement::SetPropertyTargetDirectionX</value>
                                    <value>TopDownMovementBehavior::TopDownMovementBehavior::SetVelocityX</value>
                                    <value>DebuggerTools::ConsoleLog</value>
                                <value>TopDownMovementBehavior::TopDownMovementBehavior::IsUsingControl</value>
                                                                    <value>TopDownMovementBehavior::TopDownMovementBehavior::IsUsingControl</value>
                                    <value>PixelPerfectMovement::PixelPerfectTopDownMovement::SetPropertyTargetY</value>
                                    <value>PixelPerfectMovement::PixelPerfectTopDownMovement::SetPropertyTargetDirectionY</value>
                                        <value>DebuggerTools::ConsoleLog</value>
                                <value>TopDownMovementBehavior::TopDownMovementBehavior::IsUsingControl</value>
                                                                    <value>TopDownMovementBehavior::TopDownMovementBehavior::IsUsingControl</value>
                                    <value>PixelPerfectMovement::PixelPerfectTopDownMovement::SetPropertyTargetY</value>
                                    <value>PixelPerfectMovement::PixelPerfectTopDownMovement::SetPropertyTargetDirectionY</value>
                                        <value>DebuggerTools::ConsoleLog</value>
                                <value>TopDownMovementBehavior::TopDownMovementBehavior::IsUsingControl</value>
                                <value>TopDownMovementBehavior::TopDownMovementBehavior::IsUsingControl</value>
                                                                        <value>PixelPerfectMovement::PixelPerfectTopDownMovement::PropertyTargetDirectionY</value>
                                    <value>TopDownMovementBehavior::TopDownMovementBehavior::SetVelocityY</value>
                                                                        <value>PixelPerfectMovement::PixelPerfectTopDownMovement::PropertyTargetDirectionY</value>
                                    <value>TopDownMovementBehavior::TopDownMovementBehavior::SetVelocityY</value>
                                                                                        <value>PixelPerfectMovement::PixelPerfectTopDownMovement::PropertyTargetDirectionY</value>
                                        <value>BuiltinCommonInstructions::And</value>
                                                                                        <value>PixelPerfectMovement::PixelPerfectTopDownMovement::PropertyTargetDirectionY</value>
                                        <value>BuiltinCommonInstructions::And</value>
                                    <value>BuiltinCommonInstructions::Or</value>
                                                                        <value>PixelPerfectMovement::PixelPerfectTopDownMovement::SetPropertyTargetDirectionY</value>
                                    <value>TopDownMovementBehavior::TopDownMovementBehavior::SetVelocityY</value>
                                    <value>DebuggerTools::ConsoleLog</value>
                                                                                                                                                <value>PlatformBehavior::PlatformerObjectBehavior::IsUsingControl</value>
                                                                    <value>PlatformBehavior::PlatformerObjectBehavior::IsUsingControl</value>
                                    <value>PixelPerfectMovement::PixelPerfectPlatformerCharacter::SetPropertyTargetX</value>
                                    <value>PixelPerfectMovement::PixelPerfectPlatformerCharacter::SetPropertyTargetDirectionX</value>
                                        <value>DebuggerTools::ConsoleLog</value>
                                <value>PlatformBehavior::PlatformerObjectBehavior::IsUsingControl</value>
                                                                    <value>PlatformBehavior::PlatformerObjectBehavior::IsUsingControl</value>
                                    <value>PixelPerfectMovement::PixelPerfectPlatformerCharacter::SetPropertyTargetX</value>
                                    <value>PixelPerfectMovement::PixelPerfectPlatformerCharacter::SetPropertyTargetDirectionX</value>
                                        <value>DebuggerTools::ConsoleLog</value>
                                <value>PlatformBehavior::PlatformerObjectBehavior::IsUsingControl</value>
                                <value>PlatformBehavior::PlatformerObjectBehavior::IsUsingControl</value>
                                                                        <value>PixelPerfectMovement::PixelPerfectPlatformerCharacter::PropertyTargetDirectionX</value>
                                    <value>PlatformBehavior::PlatformerObjectBehavior::SetCurrentSpeed</value>
                                                                        <value>PixelPerfectMovement::PixelPerfectPlatformerCharacter::PropertyTargetDirectionX</value>
                                    <value>PlatformBehavior::PlatformerObjectBehavior::SetCurrentSpeed</value>
                                                                                        <value>PixelPerfectMovement::PixelPerfectPlatformerCharacter::PropertyTargetDirectionX</value>
                                        <value>BuiltinCommonInstructions::And</value>
                                                                                        <value>PixelPerfectMovement::PixelPerfectPlatformerCharacter::PropertyTargetDirectionX</value>
                                        <value>BuiltinCommonInstructions::And</value>
                                    <value>BuiltinCommonInstructions::Or</value>
                                                                        <value>PixelPerfectMovement::PixelPerfectPlatformerCharacter::SetPropertyTargetDirectionX</value>
                                    <value>PlatformBehavior::PlatformerObjectBehavior::SetCurrentSpeed</value>
                                    <value>DebuggerTools::ConsoleLog</value>
                                <value>PlatformBehavior::IsOnLadder</value>
                                    <value>PlatformBehavior::PlatformerObjectBehavior::IsUsingControl</value>
                                                                            <value>PlatformBehavior::PlatformerObjectBehavior::IsUsingControl</value>
                                        <value>PixelPerfectMovement::PixelPerfectPlatformerCharacter::SetPropertyTargetY</value>
                                        <value>PixelPerfectMovement::PixelPerfectPlatformerCharacter::SetPropertyTargetDirectionY</value>
                                            <value>DebuggerTools::ConsoleLog</value>
                                    <value>PlatformBehavior::PlatformerObjectBehavior::IsUsingControl</value>
                                                                            <value>PlatformBehavior::PlatformerObjectBehavior::IsUsingControl</value>
                                        <value>PixelPerfectMovement::PixelPerfectPlatformerCharacter::SetPropertyTargetY</value>
                                        <value>PixelPerfectMovement::PixelPerfectPlatformerCharacter::SetPropertyTargetDirectionY</value>
                                            <value>DebuggerTools::ConsoleLog</value>
                                    <value>PlatformBehavior::PlatformerObjectBehavior::IsUsingControl</value>
                                    <value>PlatformBehavior::PlatformerObjectBehavior::IsUsingControl</value>
                                                                                <value>PixelPerfectMovement::PixelPerfectPlatformerCharacter::PropertyTargetDirectionY</value>
                                                                                                                        <value>PixelPerfectMovement::PixelPerfectPlatformerCharacter::PropertyTargetDirectionY</value>
                                                                                                                                        <value>PixelPerfectMovement::PixelPerfectPlatformerCharacter::PropertyTargetDirectionY</value>
                                            <value>BuiltinCommonInstructions::And</value>
                                                                                                <value>PixelPerfectMovement::PixelPerfectPlatformerCharacter::PropertyTargetDirectionY</value>
                                            <value>BuiltinCommonInstructions::And</value>
                                        <value>BuiltinCommonInstructions::Or</value>
                                                                                <value>PixelPerfectMovement::PixelPerfectPlatformerCharacter::SetPropertyTargetDirectionY</value>
                                        <value>DebuggerTools::ConsoleLog</value>
                                                                                                                                                                                                                    <value>SetWindowSize</value>
                    <value>CenterWindow</value>
                                                            <value>CentreCamera</value>
                    <value>CentreCamera</value>
                    <value>CentreCamera</value>
                    <value>SmoothCamera::SmoothCamera::MoveCameraCloser</value>
                    <value>CopyCameraSettings::CopyCameraSettings</value>
                    <value>CopyCameraSettings::CopyCameraSettings</value>
                